isgb/__init__.py
isgb-0.14.dist-info/METADATA
isgb-0.14.dist-info/WHEEL
isgb-0.14.dist-info/top_level.txt
isgb-0.14.dist-info/RECORD
