Metadata-Version: 2.4
Name: isgb
Version: 0.14
Summary: Smart import for SGB module
Home-page: https://none.com/
Author: Nikita Karachentsev
Author-email: n.karachencev@sf-m.biz
License: MIT
Requires-Dist: prettytable
Requires-Dist: colorama
Requires-Dist: grpcio
Requires-Dist: protobuf
Requires-Dist: requests
Requires-Dist: transliterate
Requires-Dist: psutil
Requires-Dist: setuptools
Requires-Dist: pycron
Requires-Dist: zeroconf
Dynamic: author
Dynamic: author-email
Dynamic: description-content-type
Dynamic: home-page
Dynamic: license
Dynamic: requires-dist
Dynamic: summary
